costgov/__init__.py
costgov/client.py
costgov/exceptions.py
costgov/test.py
costgov/validators.py
costgov-0.2.0.dist-info/licenses/LICENSE
costgov-0.2.0.dist-info/METADATA
costgov-0.2.0.dist-info/WHEEL
costgov-0.2.0.dist-info/entry_points.txt
costgov-0.2.0.dist-info/top_level.txt
costgov-0.2.0.dist-info/RECORD
