Metadata-Version: 2.4
Name: costgov
Version: 0.2.0
Summary: Python SDK for CostGov - Track and govern billable events in your application
Author-email: CostGov Team <hello@costgov.com>
License: MIT
Project-URL: Homepage, https://github.com/costgov/costgov
Project-URL: Documentation, https://docs.costgov.com
Project-URL: Repository, https://github.com/costgov/costgov
Project-URL: Issues, https://github.com/costgov/costgov/issues
Keywords: costgov,billing,tracking,events,governance,rate-limiting
Classifier: Development Status :: 4 - Beta
Classifier: Intended Audience :: Developers
Classifier: License :: OSI Approved :: MIT License
Classifier: Programming Language :: Python :: 3
Classifier: Programming Language :: Python :: 3.7
Classifier: Programming Language :: Python :: 3.8
Classifier: Programming Language :: Python :: 3.9
Classifier: Programming Language :: Python :: 3.10
Classifier: Programming Language :: Python :: 3.11
Classifier: Programming Language :: Python :: 3.12
Classifier: Topic :: Software Development :: Libraries :: Python Modules
Requires-Python: >=3.7
License-File: LICENSE
Requires-Dist: requests>=2.25.0
Provides-Extra: dev
Requires-Dist: pytest>=7.0.0; extra == "dev"
Requires-Dist: pytest-cov>=4.0.0; extra == "dev"
Requires-Dist: black>=22.0.0; extra == "dev"
Requires-Dist: mypy>=0.990; extra == "dev"
Dynamic: license-file
